README.rst
lazyseq.py
setup.py
lazyseq.egg-info/PKG-INFO
lazyseq.egg-info/SOURCES.txt
lazyseq.egg-info/dependency_links.txt
lazyseq.egg-info/top_level.txt