Metadata-Version: 1.1
Name: lazyseq
Version: 0.1.0
Summary: a lazily evaluated sequence type for Python
Home-page: http://github.com/shoyer/lazyseq
Author: Stephan Hoyer
Author-email: UNKNOWN
License: MIT
Keywords: lazy seq sequence
Platform: UNKNOWN
Classifier: Development Status :: 3 - Alpha
Classifier: Topic :: Utilities
Classifier: License :: OSI Approved :: MIT License
